klue_async
