Metadata-Version: 1.1
Name: klue-microservice-async
Version: 0.0.18
Summary: Seamless asynchronous execution of method calls inside a Klue Microservice endpoint, using celery+redis
Home-page: https://github.com/erwan-lemonnier/klue-microservice-async
Author: Erwan Lemonnier
Author-email: erwan@lemonnier.se
License: BSD
Platform: any
Classifier: Environment :: Web Environment
Classifier: Intended Audience :: Developers
Classifier: License :: OSI Approved :: BSD License
Classifier: Operating System :: OS Independent
Classifier: Programming Language :: Python
Classifier: Topic :: Internet :: WWW/HTTP :: Dynamic Content
Classifier: Topic :: Software Development :: Libraries :: Python Modules
